boxsers/__init__.py
boxsers/_boxsers_utils.py
boxsers/data_augmentation.py
boxsers/misc_tools.py
boxsers/preprocessing.py
boxsers/visual_tools.py
boxsers/machine_learning/__init__.py
boxsers/machine_learning/classification.py
boxsers/machine_learning/clustering.py
boxsers/machine_learning/deep_interpretability.py
boxsers/machine_learning/dimension_reduction.py
boxsers/machine_learning/neural_networks.py
boxsers/machine_learning/validation_metrics.py
boxsers-1.5.2.dist-info/LICENSE.txt
boxsers-1.5.2.dist-info/METADATA
boxsers-1.5.2.dist-info/WHEEL
boxsers-1.5.2.dist-info/top_level.txt
boxsers-1.5.2.dist-info/RECORD
