Metadata-Version: 2.1
Name: boxsers
Version: 1.5.2
Summary: Python package that provides a full range of functionality to process and analyze vibrational spectra (Raman, SERS, FTIR, etc.).
Home-page: https://github.com/ALebrun-108/BoxSERS
Author: Alexis Lebrun
Author-email: alexis.lebrun.1@ulaval.ca
License: MIT
Platform: UNKNOWN
Classifier: Programming Language :: Python :: 3
Classifier: License :: OSI Approved :: MIT License
Classifier: Operating System :: OS Independent
Requires-Python: >=3.6
License-File: LICENSE.txt
Requires-Dist: numpy
Requires-Dist: pandas
Requires-Dist: matplotlib
Requires-Dist: seaborn
Requires-Dist: scipy
Requires-Dist: scikit-learn
Requires-Dist: tensorflow
Requires-Dist: tables
Requires-Dist: scikit-image
